funtask/__init__.py
funtask/models/__init__.py
funtask/models/base.py
funtask/task/__init__.py
funtask/task/task1.py
farfuntask-0.0.7.dist-info/METADATA
farfuntask-0.0.7.dist-info/WHEEL
farfuntask-0.0.7.dist-info/top_level.txt
farfuntask-0.0.7.dist-info/RECORD
