Metadata-Version: 2.1
Name: farfuntask
Version: 0.0.7
Summary: farfuntask
Home-page: https://github.com/farfarfun/farfuntask
Author: bingtao
Author-email: 1007530194@qq.com
